cli2api/__init__.py
cli2api/__main__.py
cli2api/constants.py
cli2api/main.py
cli2api/api/__init__.py
cli2api/api/dependencies.py
cli2api/api/router.py
cli2api/api/utils.py
cli2api/api/v1/__init__.py
cli2api/api/v1/chat.py
cli2api/api/v1/models.py
cli2api/api/v1/responses.py
cli2api/config/__init__.py
cli2api/config/settings.py
cli2api/providers/__init__.py
cli2api/providers/claude.py
cli2api/schemas/__init__.py
cli2api/schemas/internal.py
cli2api/schemas/openai.py
cli2api/services/__init__.py
cli2api/services/completion.py
cli2api/streaming/__init__.py
cli2api/streaming/sse.py
cli2api/streaming/tool_parser.py
cli2api/tools/__init__.py
cli2api/tools/handler.py
cli2api/utils/__init__.py
cli2api/utils/logging.py
cli2api-0.2.0.dist-info/METADATA
cli2api-0.2.0.dist-info/WHEEL
cli2api-0.2.0.dist-info/entry_points.txt
cli2api-0.2.0.dist-info/RECORD
