Metadata-Version: 2.4
Name: cli2api
Version: 0.2.0
Summary: OpenAI-compatible API over Claude Code CLI
Requires-Python: >=3.11
Requires-Dist: fastapi>=0.115.0
Requires-Dist: pydantic-settings>=2.6.0
Requires-Dist: pydantic>=2.10.0
Requires-Dist: uvicorn[standard]>=0.32.0
Provides-Extra: dev
Requires-Dist: httpx>=0.28.0; extra == 'dev'
Requires-Dist: pytest-asyncio>=0.24.0; extra == 'dev'
Requires-Dist: pytest>=8.0.0; extra == 'dev'
